twisted_ipython/__init__.py
twisted_ipython/async_runner.py
twisted_ipython/config.py
twisted_ipython/magic.py
twisted_ipython-2.0.0.dist-info/LICENSE
twisted_ipython-2.0.0.dist-info/METADATA
twisted_ipython-2.0.0.dist-info/WHEEL
twisted_ipython-2.0.0.dist-info/top_level.txt
twisted_ipython-2.0.0.dist-info/RECORD
