Metadata-Version: 2.1
Name: twisted-ipython
Version: 2.0.0
Summary: An IPython extension for running twisted code
Home-page: https://github.com/jfhbrook/twisted_ipython
Author: Joshua Holbrook
Author-email: josh.holbrook@gmail.com
License: UNKNOWN
Keywords: IPython,twisted,crochet
Platform: UNKNOWN
Classifier: Programming Language :: Python
Classifier: Development Status :: 4 - Beta
Classifier: License :: OSI Approved :: BSD License
Classifier: Programming Language :: Python :: 3.7
Classifier: Framework :: IPython
Classifier: Framework :: Twisted
Requires-Dist: twisted
Requires-Dist: crochet
Requires-Dist: ipython
